README.md
setup.py
lEmoji/__init__.py
lEmoji/emoji_v11_0.py
lEmoji/emoji_v12_0.py
lEmoji/emoji_v12_1.py
lEmoji/emoji_v13_0.py
lEmoji/emoji_v13_1.py
lEmoji/emoji_v14_0.py
lEmoji/emoji_v15_0.py
lEmoji/emoji_v1_0.py
lEmoji/emoji_v2_0.py
lEmoji/emoji_v3_0.py
lEmoji/emoji_v4_0.py
lEmoji/emoji_v5_0.py
lEmoji.egg-info/PKG-INFO
lEmoji.egg-info/SOURCES.txt
lEmoji.egg-info/dependency_links.txt
lEmoji.egg-info/top_level.txt
lEmoji/data/__init__.py
lEmoji/data/tree.py
lEmoji/generator/__init__.py
lEmoji/generator/generator.py
lEmoji/generator/web_extractor.py
lemoji/__init__.py
lemoji/emoji_v11_0.py
lemoji/emoji_v12_0.py
lemoji/emoji_v12_1.py
lemoji/emoji_v13_0.py
lemoji/emoji_v1_0.py
lemoji/emoji_v2_0.py
lemoji/emoji_v3_0.py
lemoji/emoji_v4_0.py
lemoji/emoji_v5_0.py
lemoji/data/__init__.py
lemoji/data/tree.py
lemoji/generator/__init__.py
lemoji/generator/generator.py
lemoji/generator/web_extractor.py