Metadata-Version: 2.1
Name: lEmoji
Version: 15.0
Summary: emoji list for all version based on unicode.org
Home-page: https://github.com/Jyonn/lemoji
Author: Jyonn Liu
Author-email: i@6-79.cn
License: MIT Licence
Keywords: emoji
Platform: any
